<?xml version="1.0"?>
<!-- This file defines a job the AET can support for a specific ISA. -->

<?CTOOLS version="1.1.0.0" Copyright="Copyright (c) 2005-2007 Texas Instruments"?><AET>
    <JOB_MAJOR_V>1</JOB_MAJOR_V>
    <JOB_MINOR_V>0</JOB_MINOR_V>


<!--*****************************************************************************-->
<!--                       FIRST LEVEL OF FUNCTION LIST                          -->
<!-- This property presents all the supported functions to UBM and has a default -->
<!-- value of Breakpoint. Every time UBM creates a operation and calls           -->
<!-- Operation::GetProperties()this property will be returned.                   -->
<!-- The menu item showed by UBM will be look like:                              -->
<!--                                                                             -->
<!--     Type | Breakpoint         |                                             -->
<!--          | Chained Breakpoint |                                             -->
<!--          | Watchpoint         |                                             -->
<!--          | Trace              |                                             -->
<!--          | Data Access Count  |                                             -->
<!--          | Watchdog Timer     |                                             -->
<!--                                                                             -->
<!-- For different device different set of functions will be listed              -->
<!-- Mapping of The Fields:                                                      -->
<!--    NAME         - IProperty::GetName()                                      -->
<!--    DESCRIPTION  - IProperty::GetDescription()                               -->
<!--    ALLOWEDLIST  - IStringProperty::GetAllowedValues()                       -->
<!-- Other definitions:                                                          -->
<!--    ALLOWEDITEM  - defines an item of allowed values                         -->
<!--    ALLOWED_KEY  - defines the child key when this allowed value is selected -->
<!--    ALLOWED_HALT - defines if the function halts CPU                         -->
<!--    ALLOWED_STRING - allowed string value                                    -->
<!-- Every time a allowed value is selected as the value of StringProperty, the  -->
<!-- CHILDKEY will be changed. The new CHILDKEY will be used to update the child -->
<!-- property of the StringProperty                                              -->
<!--*****************************************************************************-->
	<PROPERTY_STRING>                                           
      <NAME>Type</NAME>                                         
 	  <DESCRIPTION>Display all the AET functions</DESCRIPTION>	
	  <VALUE>Trace</VALUE>
	</PROPERTY_STRING>

		
</AET>